<databaseChangeLog
        xmlns="http://www.liquibase.org/xml/ns/dbchangelog"
        xmlns:xsi="http://www.w3.org/2001/XMLSchema-instance"
        xsi:schemaLocation="
        http://www.liquibase.org/xml/ns/dbchangelog
        http://www.liquibase.org/xml/ns/dbchangelog/dbchangelog-4.31.xsd">



    <changeSet  author="priya" id="circulation-1">
        <sqlFile path="changes/loan-policy-holiday.sql"    relativeToChangelogFile="true"/>
    </changeSet>

    <changeSet  author="priya" id="circulation-2">
        <sqlFile path="changes/loan-fine-reservation.sql"    relativeToChangelogFile="true"/>
    </changeSet>

    <changeSet  author="priya" id="circulation-3">
        <sqlFile path="changes/v1_insert_holiday.sql"    relativeToChangelogFile="true"/>
    </changeSet>

    <changeSet  author="priya" id="circulation-4">
        <sqlFile path="changes/v1_insert_loan_policy.sql"    relativeToChangelogFile="true"/>
    </changeSet>

    <changeSet  author="priya" id="circulation-5">
        <sqlFile path="changes/create_wishlist_table.sql"    relativeToChangelogFile="true"/>
    </changeSet>



</databaseChangeLog>